README.md
setup.py
salesforcecli.egg-info/PKG-INFO
salesforcecli.egg-info/SOURCES.txt
salesforcecli.egg-info/dependency_links.txt
salesforcecli.egg-info/entry_points.txt
salesforcecli.egg-info/requires.txt
salesforcecli.egg-info/top_level.txt
sfcli/__init__.py
sfcli/__main__.py
sfcli/cli.py
sfcli/util.py