Metadata-Version: 2.1
Name: salesforcecli
Version: 0.0.4
Summary: A package to explore a Salesforce org, perform queries, bulk creates, updates and deletes
Home-page: https://gitlab.com/wjwatkinson/salesforcecli
Author: Will Watkinson
Author-email: wjwats4295@gmail.com
License: UNKNOWN
Platform: UNKNOWN
Classifier: Programming Language :: Python :: 3
Classifier: License :: OSI Approved :: MIT License
Classifier: Operating System :: OS Independent
Requires-Python: >=3.6
